virtual/virtual.py
virtualpy-0.0.dev2.dist-info/LICENSE
virtualpy-0.0.dev2.dist-info/METADATA
virtualpy-0.0.dev2.dist-info/WHEEL
virtualpy-0.0.dev2.dist-info/top_level.txt
virtualpy-0.0.dev2.dist-info/RECORD
