Metadata-Version: 2.1
Name: virtualpy
Version: 0.0.dev2
Summary: Virtual: The Python virtualisation software that allows you to create custom systems!
Author-email: Dylan Rogers <opendylan@proton.me>
Project-URL: Homepage, https://github.com/opendylan/virtualpy
Project-URL: Bug Tracker, https://github.com/opendylan/virtualpy/issues
Classifier: Programming Language :: Python
Classifier: License :: OSI Approved :: MIT License
Classifier: Operating System :: OS Independent
Requires-Python: >=2.0
License-File: LICENSE
